astrodb_scripts/__init__.py
astrodb_scripts/utils.py
astrodb_scripts-0.1.0.dist-info/LICENSE
astrodb_scripts-0.1.0.dist-info/METADATA
astrodb_scripts-0.1.0.dist-info/WHEEL
astrodb_scripts-0.1.0.dist-info/top_level.txt
astrodb_scripts-0.1.0.dist-info/RECORD
